mpsdk/MPSDK.py
mpsdk/__init__.py
mpsdk/__version__.py
modnpay_pgsdk-0.0.3.dist-info/METADATA
modnpay_pgsdk-0.0.3.dist-info/WHEEL
modnpay_pgsdk-0.0.3.dist-info/top_level.txt
modnpay_pgsdk-0.0.3.dist-info/RECORD
